[
  {
    "section_id": "prime_details",
    "label": {
      "en": "prime details",
      "fr": "french details",
      "ke": "swahili details"
    },
    "tabs": [
      {
        "title": "overview",
        "label": {
          "en": "overview",
          "fr": "french details",
          "ke": "swahili details"
        },
        "basic_info": {
          "title": "basic_info",
          "assignRole": {
            "en": "assign role",
            "ke": "peana jukumu",
            "fr": "attribuer un rôle"
          },
          "wef": {
            "en": "wef",
            "ke": "kuanzia tarehe",
            "fr": "à partir du"
          },
          "wet": {
            "en": "wet",
            "ke": "hadi tarehe",
            "fr": "jusqu'au"
          },
          "status": {
            "en": "status",
            "ke": "hali",
            "fr": "statut"
          }
        },
        "order": 1,
        "applicable_status": {
          "active": ["active", "suspended", "inactive", "blacklisted"],
          "inactive": ["active", "suspended", "inactive", "blacklisted"],
          "blacklisted": ["active", "suspended", "inactive", "blacklisted"],
          "ready": ["ready", "active", "blacklisted"],
          "suspended": ["active", "suspended", "inactive", "blacklisted"],
          "draft": ["draft", "ready"]
        }
      },
      {
        "title": "transactions",
        "label": {
          "en": "transactions",
          "fr": "french details",
          "ke": "swahili details"
        },
        "order": 2
      },
      {
        "title": "reports",
        "label": {
          "en": "reports",
          "fr": "french details",
          "ke": "swahili details"
        },
        "order": 3
      }
    ],
    "order": 1
  },
  {
    "section_id": "additional_information",
    "label": {
      "en": "additional information",
      "fr": "french details",
      "ke": "swahili details"
    },
    "tabs": [
      {
        "title": "prime_identity",
        "label": {
          "en": "prime identity",
          "fr": "identité principale",
          "ke": "utambulisho mkuu"
        },
        "primary_details": {
          "party_type": {
            "en": "party type",
            "fr": "type de client",
            "ke": "aina ya mteja"
          },
          "id_type": {
            "en": "Id Type",
            "fr": "type d'identifiant",
            "ke": "aina ya kitambulisho"
          },
          "id_number": {
            "en": "id number",
            "fr": "numéro d'identifiant",
            "ke": "nambari ya kitambulisho"
          },
          "pin_number": {
            "en": "pin number",
            "fr": "numéro PIN",
            "ke": "nambari ya PIN"
          },
          "dob": {
            "en": "date of birth",
            "fr": "date de naissance",
            "ke": "tarehe ya kuzaliwa"
          },
          "citizenship": {
            "en": "citizenship",
            "fr": "nationalité",
            "ke": "uraia"
          },
          "gender": {
            "en": "gender",
            "fr": "sexe",
            "ke": "jinsia"
          },
          "marital_status": {
            "en": "marital status",
            "fr": "statut matrimonial",
            "ke": "hali ya ndoa"
          }
        },
        "order": 1
      },
      {
        "title": "contact",
        "label": {
          "en": "contact",
          "fr": "french details",
          "ke": "swahili details"
        },
        "contact_details": {
          "branch": {
            "en": "branch",
            "fr": "",
            "ke": ""
          },
          "title": {
            "en": "title",
            "fr": "",
            "ke": ""
          },
          "tel_number": {
            "en": "telephone number",
            "fr": "",
            "ke": ""
          },
          "email": {
            "en": "email address",
            "fr": "",
            "ke": ""
          },
          "sms_number": {
            "en": "sms number",
            "fr": "",
            "ke": ""
          },
          "preferred_contact_channel": {
            "en": "preferred contact channel",
            "fr": "",
            "ke": ""
          }
        },
        "order": 2
      },
      {
        "title": "address",
        "label": {
          "en": "address",
          "fr": "french details",
          "ke": "swahili details"
        },
        "address_details": {
          "country": {
            "en": "country",
            "fr": "",
            "ke": ""
          },
          "county": {
            "en": "county",
            "fr": "",
            "ke": ""
          },
          "city": {
            "en": "city",
            "fr": "",
            "ke": ""
          },
          "physical_address": {
            "en": "physical address",
            "fr": "",
            "ke": ""
          },
          "postal_address": {
            "en": "postal address",
            "fr": "",
            "ke": ""
          },
          "postal_code": {
            "en": "postal code",
            "fr": "",
            "ke": ""
          },
          "town": {
            "en": "town",
            "fr": "",
            "ke": ""
          },
          "road": {
            "en": "road",
            "fr": "",
            "ke": ""
          },
          "house_no": {
            "en": "house name/no",
            "fr": "",
            "ke": ""
          }
        },
        "order": 3
      },
      {
        "title": "financial",
        "label": {
          "en": "financial",
          "fr": "french details",
          "ke": "swahili details"
        },
        "financial_details": {
          "bank_name": {
            "en": "bank name",
            "fr": "",
            "ke": ""
          },
          "branch_name": {
            "en": "branch name",
            "fr": "",
            "ke": ""
          },
          "account_number": {
            "en": "account number",
            "fr": "",
            "ke": ""
          },
          "currency": {
            "en": "currency",
            "fr": "",
            "ke": ""
          },
          "wef": {
            "en": "with effect from",
            "fr": "",
            "ke": ""
          },
          "wet": {
            "en": "with effect to",
            "fr": "",
            "ke": ""
          },
          "mobile_money_number": {
            "en": "mobile money number",
            "fr": "",
            "ke": ""
          },
          "iban": {
            "en": "iban",
            "fr": "",
            "ke": ""
          },
          "swift_code": {
            "en": "swift code",
            "fr": "",
            "ke": ""
          },
          "preferred_payment_channel": {
            "en": "preferred payment channel",
            "fr": "",
            "ke": ""
          }
        },
        "order": 5
      },
      {
        "title": "wealth_aml",
        "label": {
          "en": "wealth and aml",
          "fr": "french details",
          "ke": "swahili details"
        },
        "order": 4
      },
      {
        "title": "documents",
        "label": {
          "en": "documents",
          "fr": "french details",
          "ke": "swahili details"
        },
        "order": 7
      },
      {
        "title": "audit_trail",
        "label": {
          "en": "audit trail",
          "fr": "french details",
          "ke": "swahili details"
        },
        "order": 6
      }
    ],
    "order": 2
  }
]
